mlops_generator/__init__.py
mlops_generator/base.py
mlops_generator/cli.py
mlops_generator/interface.py
mlops_generator/persistence.py
mlops_generator/project.py
mlops_generator/prompt.py
mlops_generator/templates/.dockerignore
mlops_generator/templates/.gitignore
mlops_generator/templates/Dockerfile
mlops_generator/templates/LICENSE
mlops_generator/templates/Makefile
mlops_generator/templates/Readme.md
mlops_generator/templates/__init__.py
mlops_generator/templates/cli.py
mlops_generator/templates/cloudbuild.yaml
mlops_generator/templates/pytest.ini
mlops_generator/templates/requirements.txt
mlops_generator/templates/setup.cfg
mlops_generator/templates/setup.py
mlops_generator/templates/test_hello.py
mlops_generator/templates/components/__init__.py
mlops_generator/templates/components/base.py
mlops_generator/templates/components/temporal.py
mlops_generator/templates/components/visualization.py
mlops_generator/templates/components/{{cloud_storage}}.py
mlops_generator/templates/components/{{jupyter}}.ipynb
mlops_generator/templates/components/{{kfp_cop}}.py
mlops_generator/templates/components/{{pandas}}.py
mlops_generator/templates/components/{{pipeline}}.py
mlops_generator/templates/components/{{sklearn}}.py
mlops_generator-1.0.1.dist-info/AUTHORS.rst
mlops_generator-1.0.1.dist-info/LICENSE
mlops_generator-1.0.1.dist-info/METADATA
mlops_generator-1.0.1.dist-info/WHEEL
mlops_generator-1.0.1.dist-info/entry_points.txt
mlops_generator-1.0.1.dist-info/top_level.txt
mlops_generator-1.0.1.dist-info/RECORD
