Metadata-Version: 2.1
Name: mlops-generator
Version: 1.0.1
Summary: CLI for MLOps code generator
Home-page: https://github.com/averagua/mlops_generator
Author: Alejandro Veragua Albornoz
Author-email: veragua.alb@gmail.com
License: MIT license
Keywords: mlops_generator
Platform: UNKNOWN
Classifier: Development Status :: 2 - Pre-Alpha
Classifier: Intended Audience :: Developers
Classifier: License :: OSI Approved :: MIT License
Classifier: Natural Language :: English
Classifier: Programming Language :: Python :: 3
Classifier: Programming Language :: Python :: 3.5
Classifier: Programming Language :: Python :: 3.6
Classifier: Programming Language :: Python :: 3.7
Classifier: Programming Language :: Python :: 3.8
Requires-Python: >=3.5
Requires-Dist: click (>=7.0)
Requires-Dist: marshmallow (==3.9.1)
Requires-Dist: jinja2 (==2.11)
